tests/__init__.py
tests/fixtures.py
tests/test_filters.py
tests/test_main.py
tests/test_twempest.py
twempest/__init__.py
twempest/__main__.py
twempest/filters.py
twempest/twempest.py
twempest-0.2.12.dist-info/LICENSE
twempest-0.2.12.dist-info/METADATA
twempest-0.2.12.dist-info/WHEEL
twempest-0.2.12.dist-info/entry_points.txt
twempest-0.2.12.dist-info/top_level.txt
twempest-0.2.12.dist-info/RECORD
