Metadata-Version: 2.1
Name: twempest
Version: 0.2.12
Summary: Twitter to text via template. Somehow that abbreviates to "twempest".
Home-page: https://github.com/yukondude/Twempest
Author: Dave Rogers
Author-email: thedude@yukondude.com
License: GPLv3
Platform: MacOS
Platform: Linux
Classifier: Development Status :: 4 - Beta
Classifier: Environment :: Console
Classifier: Intended Audience :: Developers
Classifier: Intended Audience :: End Users/Desktop
Classifier: License :: OSI Approved :: GNU General Public License v3 (GPLv3)
Classifier: Natural Language :: English
Classifier: Operating System :: MacOS
Classifier: Operating System :: POSIX
Classifier: Operating System :: POSIX :: Linux
Classifier: Programming Language :: Python
Classifier: Programming Language :: Python :: 3
Classifier: Programming Language :: Python :: 3.6
Classifier: Programming Language :: Python :: 3.7
Classifier: Topic :: Text Processing
Classifier: Topic :: Utilities
Requires-Dist: click (>=7.0)
Requires-Dist: pytz (>=2018.7)
Requires-Dist: tweepy (>=3.7.0)
Requires-Dist: tzlocal (>=1.5.1)
Requires-Dist: jinja2 (>=2.10)
Requires-Dist: pipenv
